djangopyetl/__init__.py
djangopyetl/admin.py
djangopyetl/asgi.py
djangopyetl/helpers.py
djangopyetl/settings.py
djangopyetl/tests.py
djangopyetl/urls.py
djangopyetl/wsgi.py
djangopyetl-0.1.5.dist-info/LICENSE
djangopyetl-0.1.5.dist-info/WHEEL
djangopyetl-0.1.5.dist-info/METADATA
djangopyetl-0.1.5.dist-info/RECORD
