Metadata-Version: 2.1
Name: djangopyetl
Version: 0.1.5
Summary: Django app for ETL
Author: MacSoares
Author-email: macario.junior@gmail.com
Requires-Python: >=3.7.1,<3.11
Classifier: Programming Language :: Python :: 3
Classifier: Programming Language :: Python :: 3.10
Classifier: Programming Language :: Python :: 3.8
Classifier: Programming Language :: Python :: 3.9
Requires-Dist: Django (>=3.1,<4.0)
Requires-Dist: SQLAlchemy (>=1.4.26,<2.0.0)
Requires-Dist: ipython (>=7.28.0,<8.0.0)
Requires-Dist: numpy (>=1.21.3,<2.0.0)
Requires-Dist: pandas (==1.3.4)
Requires-Dist: pyodbc (>=4.0.32,<5.0.0)
